mb_capcha_ocr/__init__.py
mb_capcha_ocr/model.onnx
mb_capcha_ocr/predict.py
mb_capcha_ocr-0.1.5.dist-info/licenses/LICENSE
mb_capcha_ocr-0.1.5.dist-info/METADATA
mb_capcha_ocr-0.1.5.dist-info/WHEEL
mb_capcha_ocr-0.1.5.dist-info/top_level.txt
mb_capcha_ocr-0.1.5.dist-info/RECORD
