Metadata-Version: 2.4
Name: mb_capcha_ocr
Version: 0.1.5
Summary: An pytorch ocr base library for MBBank lib
Home-page: https://github.com/thedtvn/mbbank-capcha-ocr
Author: The DT
License: MIT
License-File: LICENSE
Requires-Dist: onnxruntime
Requires-Dist: pillow
Requires-Dist: numpy
Requires-Dist: setuptools
Requires-Dist: wheel
Dynamic: author
Dynamic: description
Dynamic: description-content-type
Dynamic: home-page
Dynamic: license
Dynamic: license-file
Dynamic: requires-dist
Dynamic: summary
